Workbook

Sheet Итог
A1: Три сценария
A2: Склад, перевозка паллет между зонами · Ronavi H1500 (грузоподъемность до 1 500 кг) · расчет от 18.10.2026 22:58 мск · модель 0.2
A3: Предварительная оценка, не коммерческое предложение
A5: Показатель | B5: Без роботов | C5: Покупка | D5: Аренда | E5: Как посчитано
A6: Стоимость владения за 5 лет | B6: ='По годам'!G11 | C6: ='По годам'!G17 | D6: ='По годам'!G23 | E6: Накопленные затраты последнего года на листе "По годам"
A7: Вложения на старте | B7: ='По годам'!E6 | C7: ='По годам'!E12 | D7: ='По годам'!E18 | E7: Год 0 на листе "По годам"
A8: Затраты за 5 лет без вложений | B8: =B6-B7 | C8: =C6-C7 | D8: =D6-D7 | E8: Стоимость владения - вложения на старте
A9: Дешевле, чем без роботов | B9: — | C9: =B6-C6 | D9: =B6-D6 | E9: Стоимость владения без роботов - стоимость владения сценария
A10: Годовой эффект, первый год | B10: — | C10: ='По годам'!H13 | D10: ='По годам'!H19 | E10: Год 1 на листе "По годам"
A11: Окупаемость по ТЗ, лет | B11: — | C11: 1.0660414 | D11: 0.3567246 | E11: Все вложения проекта / эффект первого года, как бы за них ни платили. Считает сервер
A12: Окупаемость по потоку, лет | B12: — | C12: 1.0598008 | D12: 0.3567246 | E12: Когда накопленная экономия перекроет вложения, с ростом цен и выкупом. Считает сервер
A13: ROI за 5 лет | B13: — | C13: 4.5139005 | D13: 16.143787 | E13: Сколько заработали сверх вложений: (экономия за 5 лет - вложения) / вложения. 0% значит, что вложения только вернулись
A14: Экономия на рубль вложений (ROI по формуле ТЗ) | B14: — | C14: 5.5139005 | D14: 17.143787 | E14: Экономия за 5 лет / вложения. 1 раз значит, что вложения только вернулись
A15: NPV | B15: — | C15: 89602500 | D15: 91406069 | E15: Чистая приведенная стоимость, считает сервер
A16: IRR проекта | B16: — | C16: 0.97552497 | D16: больше 100% | E16: Ставка, при которой NPV = 0, без схемы оплаты. Выше 100% пишем словами: вложения возвращаются быстрее, чем за год
A17: Выкуп в конце 3 года, цена | B17: — | C17: — | D17: 7967213.1 | E17: Аренда без выкупа базовая. Выкуп по остаточной стоимости: роботы * цена * (1 - договор / срок службы)
A18: Аренда в год после договора | B18: — | C18: — | D18: 10186344 | E18: Плата и ответственность за порчу, среднее по годам после конца договора
A19: Свои роботы в год после выкупа | B19: — | C19: — | D19: 2793166.4 | E19: ТО, лицензии, замена АКБ и обновление парка, среднее
A20: Выкуп окупится, лет | B20: — | C20: — | D20: 1.0776439 | E20: Цена выкупа / (аренда в год - свои роботы в год)
A21: С выкупом дешевле за 5 лет | B21: — | C21: — | D21: 6819142.6 | E21: Стоимость владения аренды без выкупа - с выкупом. Минус: выкуп не успевает окупиться
A23: Вывод
A24: Покупка, до 3 лет: Вложения возвращаются за 1,1 года, за горизонт операция дешевеет на 149,1 млн рублей.
A25: Аренда, до 3 лет: Аренда выгоднее людей с первого года: экономия 24,4 млн рублей в год после платежей, внедрение 8,7 млн рублей вернется за 0,4 года. За горизонт операция дешевеет на 140,4 млн рублей.
A27: Что может сдвинуть вывод
A28: 1. План объекта вы не чертили: мы взяли типовую планировку склада, поэтому где на вашем объекте стоят ворота и зоны хранения, нам неизвестно, а от этого зависит длина маршрута
A29: 2. Выход на режим: в первый год экономия меньше на 0,9 млн рублей. Сколько месяцев роботы работают не на полную, никто не публикует, это наше допущение
A30: 3. Ronavi Robotics H1500 возит паллеты по полу, а верхний ярус на плане 6,8 м. Кто ставит груз в стеллаж, проверьте: расчет отдает роботу 74% работы водителя погрузчика, если ставит водитель, часть его ставок останется

Sheet По годам
A1: Сценарии по годам
A2: Склад, перевозка паллет между зонами · Ronavi H1500 (грузоподъемность до 1 500 кг) · расчет от 18.10.2026 22:58 мск · модель 0.2
A3: Предварительная оценка, не коммерческое предложение
A5: Сценарий | B5: Год | C5: Люди на операции, ₽ | D5: Роботы: операторы, обслуживание, энергия, аренда, ₽ | E5: Вложения, платежи по долгу минус господдержка, ₽ | F5: Затраты за год, ₽ | G5: Накопленные затраты, ₽ | H5: Эффект против работы без роботов, ₽ | I5: Денежный поток, ₽
A6: Без роботов | B6: 0 | C6: 0 | D6: 0 | E6: 0 | F6: =C6+D6+E6 | G6: =F6
A7: Без роботов | B7: 1 | C7: 37114095 | D7: 0 | E7: 0 | F7: =C7+D7+E7 | G7: =G6+F7 | H7: 0 | I7: 0
A8: Без роботов | B8: 2 | C8: 39712081 | D8: 0 | E8: 0 | F8: =C8+D8+E8 | G8: =G7+F8 | H8: 0 | I8: 0
A9: Без роботов | B9: 3 | C9: 42491927 | D9: 0 | E9: 0 | F9: =C9+D9+E9 | G9: =G8+F9 | H9: 0 | I9: 0
A10: Без роботов | B10: 4 | C10: 45466362 | D10: 0 | E10: 0 | F10: =C10+D10+E10 | G10: =G9+F10 | H10: 0 | I10: 0
A11: Без роботов | B11: 5 | C11: 48649007 | D11: 0 | E11: 0 | F11: =C11+D11+E11 | G11: =G10+F11 | H11: 0 | I11: 0
A12: Покупка | B12: 0 | C12: 0 | D12: 0 | E12: 33039647 | F12: =C12+D12+E12 | G12: =F12
A13: Покупка | B13: 1 | C13: 927852.36 | D13: 5193405.3 | E13: 0 | F13: =C13+D13+E13 | G13: =G12+F13 | H13: 30992837 | I13: 30992837
A14: Покупка | B14: 2 | C14: 0 | D14: 5484948.7 | E14: 0 | F14: =C14+D14+E14 | G14: =G13+F14 | H14: 34227132 | I14: 34227132
A15: Покупка | B15: 3 | C15: 0 | D15: 7055088.9 | E15: 0 | F15: =C15+D15+E15 | G15: =G14+F15 | H15: 35436838 | I15: 35436838
A16: Покупка | B16: 4 | C16: 0 | D16: 6122960.5 | E16: 0 | F16: =C16+D16+E16 | G16: =G15+F16 | H16: 39343401 | I16: 39343401
A17: Покупка | B17: 5 | C17: 0 | D17: 6471889.6 | E17: 0 | F17: =C17+D17+E17 | G17: =G16+F17 | H17: 42177117 | I17: 42177117
A18: Аренда | B18: 0 | C18: 0 | D18: 0 | E18: 8695384.7 | F18: =C18+D18+E18 | G18: =F18
A19: Аренда | B19: 1 | C19: 927852.36 | D19: 11810618 | E19: 0 | F19: =C19+D19+E19 | G19: =G18+F19 | H19: 24375624 | I19: 24375624
A20: Аренда | B20: 2 | C20: 0 | D20: 12012752 | E20: 0 | F20: =C20+D20+E20 | G20: =G19+F20 | H20: 27699329 | I20: 27699329
A21: Аренда | B21: 3 | C21: 0 | D21: 12229221 | E21: 0 | F21: =C21+D21+E21 | G21: =G20+F21 | H21: 30262706 | I21: 30262706
A22: Аренда | B22: 4 | C22: 0 | D22: 13566425 | E22: 0 | F22: =C22+D22+E22 | G22: =G21+F22 | H22: 31899936 | I22: 31899936
A23: Аренда | B23: 5 | C23: 0 | D23: 13814781 | E23: 0 | F23: =C23+D23+E23 | G23: =G22+F23 | H23: 34834227 | I23: 34834227

Sheet Затраты
A1: Затраты по статьям
A2: Склад, перевозка паллет между зонами · Ronavi H1500 (грузоподъемность до 1 500 кг) · расчет от 18.10.2026 22:58 мск · модель 0.2
A3: Предварительная оценка, не коммерческое предложение
A5: Статья | B5: Когда | C5: Покупка, ₽ | D5: Аренда, ₽
A6: Роботы | B6: разово | C6: 19918033 | D6: 0
A7: Зарядные станции | B7: разово | C7: 1106557.4 | D7: 0
A8: ПО управления парком | B8: разово | C8: 1106557.4 | D8: 0
A9: Станции комплектации | B9: разово | C9: 0 | D9: 0
A10: Интеграция с WMS | B10: разово | C10: 3688524.6 | D10: 3688524.6
A11: Инфраструктура | B11: разово | C11: 2213114.8 | D11: 2213114.8
A12: Пусконаладка | B12: разово | C12: 1991803.3 | D12: 1991803.3
A13: Переобучение операторов | B13: разово | C13: 11452.523 | D13: 11452.523
A14: Резерв | B14: разово | C14: 3003604.3 | D14: 790489.51
A15: Электроэнергия | B15: 1 год | C15: 383860.33 | D15: 383860.33
A16: Связь | B16: 1 год | C16: 221311.48 | D16: 221311.48
A17: Операторы роботов | B17: 1 год | C17: 2153807.3 | D17: 2153807.3
... A54: Ответственность за порчу | B54: 5 год | C54: 0 | D54: 233012.81

Sheet Что будет, если
A1: Что будет, если
A2: Склад, перевозка паллет между зонами · Ronavi H1500 (грузоподъемность до 1 500 кг) · расчет от 18.10.2026 22:58 мск · модель 0.2
A3: Предварительная оценка, не коммерческое предложение
A4: Одно число сдвигаем, остальные как в расчете. При сдвиге объема парк растет вместе со спросом
A5: Параметр | B5: Сдвиг | C5: Роботов | D5: Покупка: окупаемость, лет | E5: Покупка: владение за 5 лет, ₽ | F5: Аренда: окупаемость, лет | G5: Аренда: владение за 5 лет, ₽ | H5: Что меняется
A6: Зарплаты | B6: -20% | C6: 9 | D6: 1.3268132 | E6: 61635148 | F6: 0.49260283 | G6: 70396390 | H6: оклады всех ролей в штате. Дороже люди на операции без роботов и операторы роботов с ними: окупаемость лучше
A7: Зарплаты | B7: -10% | C7: 9 | D7: 1.1771485 | E7: 62965470 | F7: 0.41379459 | G7: 71726712
A8: Зарплаты | B8: как сейчас | C8: 9 | D8: 1.0598008 | E8: 64295792 | F8: 0.3567246 | G8: 73057035
A9: Зарплаты | B9: +10% | C9: 9 | D9: 0.96172159 | E9: 65626115 | F9: 0.31348867 | G9: 74387357
A10: Зарплаты | B10: +20% | C10: 9 | D10: 0.87599882 | E10: 66956437 | F10: 0.27960039 | G10: 75717679
A11: Цена робота | B11: -20% | C11: 9 | D11: 0.89896166 | E11: 57317979 | F11: 0.33819506 | G11: 72403073 | H11: 2 700 000 ₽ за робота. С ценой меняются вложения, пусконаладка, ТО, выкуп после аренды и ответственность за порчу
A12: Цена робота | B12: -10% | C12: 9 | D12: 0.98196807 | E12: 60806885 | F12: 0.34745227 | G12: 72730054
A13: Цена робота | B13: как сейчас | C13: 9 | D13: 1.0598008 | E13: 64295792 | F13: 0.3567246 | G13: 73057035
A14: Цена робота | B14: +10% | C14: 9 | D14: 1.1368629 | E14: 67784699 | F14: 0.3660121 | G14: 73384015
A15: Цена робота | B15: +20% | C15: 9 | D15: 1.2148691 | E15: 71273606 | F15: 0.3753148 | G15: 73710996
A16: Объем задачи | B16: -20% | C16: 8 | D16: 0.9217039 | E16: 56984418 | F16: 0.30088977 | G16: 65042681 | H16: 2 000 операций в сутки. Больше работы, больше роботов. Людей на операции столько, сколько в штате: штат вы ввели сами, и от объема он не меняется
A17: Объем задачи | B17: -10% | C17: 9 | D17: 1.0598008 | E17: 64295792 | F17: 0.3567246 | G17: 73057035
A18: Объем задачи | B18: как сейчас | C18: 9 | D18: 1.0598008 | E18: 64295792 | F18: 0.3567246 | G18: 73057035
A19: Объем задачи | B19: +10% | C19: 10 | D19: 1.1832274 | E19: 71201429 | F19: 0.41891337 | G19: 81071388
A20: Объем задачи | B20: +20% | C20: 11 | D20: 1.2852618 | E20: 77250508 | F20: 0.45544397 | G20: 88364430
A21: Плата за аренду | B21: -20% | C21: 9 | D21: 1.0598008 | E21: 64295792 | F21: 0.33256889 | G21: 63762434 | H21: 100 000 ₽ в месяц за робота. Меняет только аренду: покупка от нее не зависит
A22: Плата за аренду | B22: -10% | C22: 9 | D22: 1.0598008 | E22: 64295792 | F22: 0.34422349 | G22: 68409734
A23: Плата за аренду | B23: как сейчас | C23: 9 | D23: 1.0598008 | E23: 64295792 | F23: 0.3567246 | G23: 73057035
A24: Плата за аренду | B24: +10% | C24: 9 | D24: 1.0598008 | E24: 64295792 | F24: 0.37016793 | G24: 77704335
A25: Плата за аренду | B25: +20% | C25: 9 | D25: 1.0598008 | E25: 64295792 | F25: 0.38466418 | G25: 82351635
A26: Внедрение | B26: -20% | C26: 9 | D26: 1.0218671 | E26: 62997432 | F26: 0.30345989 | G26: 71758674 | H26: интеграция и инфраструктура 8 000 000 ₽. Разовые затраты на старте: связь с учетной системой и переделка объекта. Цифр рынка нет, это оценка
A27: Внедрение | B27: -10% | C27: 9 | D27: 1.040834 | E27: 63646612 | F27: 0.33009224 | G27: 72407854
A28: Внедрение | B28: как сейчас | C28: 9 | D28: 1.0598008 | E28: 64295792 | F28: 0.3567246 | G28: 73057035
A29: Внедрение | B29: +10% | C29: 9 | D29: 1.0787676 | E29: 64944973 | F29: 0.38335696 | G29: 73706215
A30: Внедрение | B30: +20% | C30: 9 | D30: 1.0977345 | E30: 65594153 | F30: 0.40998932 | G30: 74355395
A32: Все числа по силе влияния
A33: Каждое число по одному на -20% и +20%. Размах: насколько меняется выгода против работы без роботов
A34: Число | B34: Сейчас | D34: Покупка: размах выгоды за 5 лет, ₽ | E34: Покупка: окупаемость при -20% и +20% | F34: Аренда: размах выгоды за 5 лет, ₽ | G34: Аренда: окупаемость при -20% и +20% | H34: Путь в модели
A35: Доля работы людей, которую забирает робот, перевозка паллет между зонами | B35: 74% | D35: 85002248 | E35: 1,4 -> 0,9 | F35: 85002248 | G35: 0,5 -> 0,3 | H35: facilities.warehouse.operations.pallet_transport.labor_share
A36: Людей в штате, оператор погрузчика | B36: 25 человек | D36: 85002248 | E36: 1,4 -> 0,9 | F36: 85002248 | G36: 0,5 -> 0,3 | H36: facilities.warehouse.staff.forklift-operators.headcount
A37: Оклад в месяц, оператор погрузчика | B37: 120 000 ₽ в месяц | D37: 79075583 | E37: 1,3 -> 0,9 | F37: 79075583 | G37: 0,5 -> 0,3 | H37: facilities.warehouse.staff.forklift-operators.salary_month
A38: Продолжительность смены | B38: 11 ч | D38: 21721188 | E38: 1,4 -> не справится | F38: 25317832 | G38: 0,5 -> не справится | H38: facilities.warehouse.schedule.shift_hours
A39: Объем задачи в сутки, перевозка паллет между зонами | B39: 2 000 в сутки | D39: 20266089 | E39: 0,9 -> 1,3 | F39: 23321749 | G39: 0,3 -> 0,5 | H39: facilities.warehouse.operations.pallet_transport.volume_per_day
A40: Средняя скорость | B40: 1 м/с | D40: 20266089 | E40: 1,3 -> 0,9 | F40: 23321749 | G40: 0,5 -> 0,3 | H40: robots.ronavi-h1500.avg_speed_m_s
A41: Роботов в строю | B41: 90% | D41: 19003794 | E41: 1,4 -> 1,1 | F41: 22600438 | G41: 0,5 -> 0,4 | H41: engine.simulation.availability
A42: Пиковый коэффициент нагрузки | B42: 1,5 раза | D42: 17349275 | E42: 0,9 -> 1,3 | F42: 20404935 | G42: 0,3 -> 0,5 | H42: facilities.warehouse.peak_factor
A43: Аренда в месяц | B43: 100 000 ₽ в месяц за робота | D43: 0 | E43: 1,1 -> 1,1 | F43: 18589201 | G43: 0,3 -> 0,4 | H43: robots.ronavi-h1500.raas.fee_rub_month
A44: Страховые взносы | B44: 30% оклада | D44: 18164376 | E44: 1,1 -> 1,0 | F44: 18164376 | G44: 0,4 -> 0,3 | H44: economics.payroll.insurance_rate
A45: Доля работы, посильная роботам, перевозка паллет между зонами | B45: 95% | D45: 14217010 | E45: 0,9 -> 1,2 | F45: 16028707 | G45: 0,3 -> 0,4 | H45: facilities.warehouse.operations.pallet_transport.automatable_share
A46: Цена робота | B46: 2 700 000 ₽ | D46: 13955627 | E46: 0,9 -> 1,2 | F46: 1307923.4 | G46: 0,3 -> 0,4 | H46: robots.ronavi-h1500.price_rub
... A73: Переобучение одного человека | B73: 10 000 ₽ на человека | D73: 5039.11 | E73: 1,1 -> 1,1 | F73: 5039.11 | G73: 0,4 -> 0,4 | H73: facilities.warehouse.implementation.retraining_rub_per_person
A75: Итог не двигают при сдвиге до 20%: Предельная база страховых взносов, Взносы сверх предельной базы, Площадь робозоны на робота отбора, Площадь зоны работы роботов, Доля отборов ходового товара, Доля ходового товара, Подбор оператора, Постоянные вложения пилота, доля, Вес груза, перевозка паллет между зонами, Часть склада под отбор роботами, Активных SKU, Время зарядки, Работа от одной зарядки
A77: Равны нулю, в процентах их не сдвинуть: Текучесть персонала в год, Спецодежда на человека в год, Надбавка оператору роботов, Рейсов в час по паспорту, Присмотр за парком в аренде, Цена станции комплектации

Sheet Парк и штат
A1: Парк роботов и штат
A2: Склад, перевозка паллет между зонами · Ronavi H1500 (грузоподъемность до 1 500 кг) · расчет от 18.10.2026 22:58 мск · модель 0.2
A3: Предварительная оценка, не коммерческое предложение
A5: Что | B5: Перевозка паллет между зонами
A6: Решение | B6: Ronavi H1500 (грузоподъемность до 1 500 кг)
A7: Производитель | B7: ООО "Ронави Роботикс"
A8: Цена решения из каталога, ₽ | B8: 2700000
A9: Откуда размер парка | B9: прогон смены
A10: Роботов | B10: 9
A11: Зарядных станций | B11: 3
A12: Станций комплектации | B12: 0
A13: Спрос в пиковый час, операций | B13: 148.97727
A14: Робот делает операций в час | B14: 17.82646
A15: Средний маршрут, м | B15: 65.730122
A16: Присмотр за роботами, человек в смену | B16: 0.225
A17: Людей на операции в смену, было | B17: 3.6345704
A18: Людей на операции в смену, стало | B18: 0.225
A19: Высвобождено ставок | B19: 18.5
A20: Из них переучиваем в операторов | B20: 1.1452523
A22: Роль | B22: Мест в штате | C22: Из них работает | D22: Оклад в месяц, ₽ | E22: По договору
A23: Оператор погрузчика | B23: 25 | C23: 25 | D23: 120000 | E23: нет

Sheet Цена операции
A1: Цена одной операции
A2: Склад, перевозка паллет между зонами · Ronavi H1500 (грузоподъемность до 1 500 кг) · расчет от 18.10.2026 22:58 мск · модель 0.2
A3: Предварительная оценка, не коммерческое предложение
A4: Все расходы за 5 лет, деленные на число операций за те же годы
A5: Задача | B5: Операций за горизонт | C5: Без роботов | D5: Покупка | E5: Аренда
A6: ₽ за перевозку паллеты | B6: 3650000 | C6: 58.474924 | D6: 17.615286 | E6: 20.015626

Sheet Вопросы поставщику
A1: Что спросить у поставщика
A2: Склад, перевозка паллет между зонами · Ronavi H1500 (грузоподъемность до 1 500 кг) · расчет от 18.10.2026 22:58 мск · модель 0.2
A3: Предварительная оценка, не коммерческое предложение
A5: № | B5: Тема | C5: Вопрос | D5: Почему важно
A6: 1 | B6: Зарядка | C6: Сколько зарядных станций нужно при нашей смене и парке в 9 шт., как долго робот заряжается и можно ли менять батарею на ходу? В расчете их 3. | D6: Число зарядок и время простоя на заряде сдвигают размер парка и вложения
A7: 2 | B7: Связь с WMS | C7: Как робот подключается к нашей складской системе: какие интерфейсы, кто делает интеграцию и сколько она стоит? | D7: Интеграция стоит отдельной статьей вложений, ее цену называет только тот, кто будет делать
A8: 3 | B8: Сервис | C8: Кто и за сколько часов приезжает на ремонт, есть ли склад запчастей в России и что входит в абонентское обслуживание? | D8: Простой робота без сервиса съедает экономию, обслуживание идет в расходы каждый год
A9: 4 | B9: Сроки | C9: Через сколько недель после оплаты роботы будут на складе и запущены, из чего складывается этот срок? | D9: Пока идет запуск, экономии нет, а платить начинаете раньше
A10: 5 | B10: Обучение | C10: Кто обучает наших людей, сколько часов это занимает и входит ли обучение в цену? | D10: Операторов и обучение расчет считает отдельно
A11: 6 | B11: Гарантия | C11: Какой срок гарантии, что она покрывает и сколько служит батарея до замены? | D11: Срок службы и замена батарей влияют на расходы в последние годы горизонта
A12: 7 | B12: Что входит в цену | C12: Входит ли в цену НДС, доставка, пусконаладка, программное обеспечение и лицензии на следующие годы? | D12: Цена в каталоге это цена изделия, без доставки, пусконаладки и интеграции
A13: 8 | B13: Наш склад | C13: Подтвердите письменно, что робот проедет по нашему плану: ширина проезда, покрытие пола, уклоны и высота подъема. | D13: Расчет проверяет это по каталогу, а подтверждение дает только поставщик
A14: 9 | B14: Пилот | C14: Можно ли сначала взять один-два робота на пилот и на каких условиях вернуть или докупить остальные? | D14: Пилот проверяет цифры расчета на вашем складе до большой покупки
A15: 10 | B15: Сбои | C15: Что делает робот при потере связи или препятствии на проезде и как быстро склад возвращается к работе вручную? | D15: Склад не должен вставать, пока чинят робота

Sheet Смена
A1: Смена на плане
A2: Склад, перевозка паллет между зонами · Ronavi H1500 (грузоподъемность до 1 500 кг) · расчет от 18.10.2026 22:58 мск · модель 0.2
A3: Предварительная оценка, не коммерческое предложение
A4: Прогон смены тем парком, что в расчете: пик спроса, очереди и зарядка
A5: Что | B5: Перевозка паллет между зонами
A6: Решение | B6: Ronavi H1500 (грузоподъемность до 1 500 кг)
A7: Роботов в прогоне | B7: 9
A8: Часов смены | B8: 8
A9: Единица задачи | B9: паллет
A10: Пик спроса с запасом, в час | B10: 148.97727
A11: Сделано за смену | B11: 748
A12: В среднем за смену, в час | B12: 93.5
A13: Роботы в работе, доля времени | B13: 0.48679784
A14: Ждут в очереди, доля времени | B14: 0
A15: На зарядке, доля времени | B15: 0.025
A16: Средний рейс, с | B16: 168.20321
A17: Узкое место | B17: парк взят под пик спроса: 49% времени смены роботы без задания, в основном вне пика
A18: План | B18: типовой

Sheet Параметры
A1: Параметры объекта
A2: Склад, перевозка паллет между зонами · Ronavi H1500 (грузоподъемность до 1 500 кг) · расчет от 18.10.2026 22:58 мск · модель 0.2
A3: Предварительная оценка, не коммерческое предложение
A5: Параметр | B5: Значение | C5: Единица | D5: Доверие | E5: Поправлено | F5: Источник
A6: Смен в сутки | B6: 2 | C6: смен | D6: B | F6: Отраслевой датасет по складам, лист "Склад"; сходится с вакансиями РЦ и фулфилмента 2/2 день и ночь (docs/decisions.md, "Типовой режим склада")
A7: Продолжительность смены | B7: 11 | C7: ч | D7: B | F7: Режим склада без выходных, сверка 19.10.2026. В датасете, лист "Склад", 2 смены по 11 ч 365 дней, и так работают склады обоих типов: РЦ Магнита в Подольске 2/2 по 11 ч с ночными часами (hh.ru/vacancy/135864165, 15.10.2026), Ленты в Валищево 2/2 по 12 ч (hh.ru/vacancy/135995269), FM Logistic Белый Раст 2/2 день и ночь по 12 ч (hh.ru/vacancy/135967197), Мегамаркет в Москве 2/2 ночь 20:00-08:00 (hh.ru/vacancy/135946119), даркстор Лавки ночь 21:00-9:00 (hh.ru/vacancy/135852510, 28.09.2026). Пятидневки 2 смены по 8 ч у РЦ и фулфилмента не нашли. Берем 22 часа датасета, а не 24 у вакансий: так экономия не завышена. Свой режим человек ставит на шаге параметров (docs/decisions.md, "Типовой режим склада")
A8: Рабочих дней в году | B8: 365 | C8: дн | D8: B | F8: Режим склада без выходных, сверка 19.10.2026. В датасете, лист "Склад", 2 смены по 11 ч 365 дней, и так работают склады обоих типов: РЦ Магнита в Подольске 2/2 по 11 ч с ночными часами (hh.ru/vacancy/135864165, 15.10.2026), Ленты в Валищево 2/2 по 12 ч (hh.ru/vacancy/135995269), FM Logistic Белый Раст 2/2 день и ночь по 12 ч (hh.ru/vacancy/135967197), Мегамаркет в Москве 2/2 ночь 20:00-08:00 (hh.ru/vacancy/135946119), даркстор Лавки ночь 21:00-9:00 (hh.ru/vacancy/135852510, 28.09.2026). Пятидневки 2 смены по 8 ч у РЦ и фулфилмента не нашли. Берем 22 часа датасета, а не 24 у вакансий: так экономия не завышена. Свой режим человек ставит на шаге параметров (docs/decisions.md, "Типовой режим склада")
A9: Пиковый коэффициент нагрузки | B9: 1.5 | D9: D | F9: Отраслевой датасет по складам, лист "Склад"
A10: Компания возвращает НДС? | B10: 0 | C10: 1 не возвращает, 0 возвращает | D10: F | F10: Выбор клиента: 1 компания не возвращает НДС (упрощенка без НДС), считаем цены с НДС; 0 возвращает, цены без НДС. По умолчанию 0: склад на общей системе налогов возвращает входной НДС, и с 2026 года на НДС переходят компании на УСН с выручкой больше 20 млн (425-ФЗ)
A11: Товар разложен по ходовости | B11: 0 | C11: 1 да, 0 нет | D11: F | F11: Выбор клиента: разложен ли товар по ходовости, 1 да, 0 нет. По умолчанию нет: так расчет осторожнее, а на Восток-Сервисе роботов и без этого вышло вдвое больше нашей формулы
A12: Площадь зоны работы роботов | B12: 10000 | C12: м2 | D12: D | F12: Отраслевой датасет по складам, лист "Склад"
A13: Активных SKU | B13: 2000 | C13: SKU | D13: D | F13: Отраслевой датасет по складам, лист "Склад": активных SKU 2000 (1000-10000). В расчет не входит, описание склада для отчета
A14: Роботов в строю | B14: 0.9 | C14: доля | D14: F | F14: Что остается от коэффициента загрузки после симуляции: очереди и зарядку она считает сама, остаются плановое ТО и мелкие простои. Источника нет, допущение команды
A15: Потери рабочего времени | B15: 0.25 | C15: доля | D15: D | F15: Отраслевой датасет по складам, лист "Склад": +25% к нормативной численности
A16: Минимум операторов в смене | B16: 0 | C16: чел | D16: F | F16: Выбор пользователя: сколько дежурных по роботам держать в смене всегда, сверх присмотра по нагрузке. По умолчанию 0: присмотр считаем долей поста от минут внимания на робота, это часть работы начальника смены или оператора соседней зоны. Норматива роботов на оператора для складских AMR никто не публикует; Vecna Robotics на первых внедрениях видела 1 человека на 4-10 роботов и называет это неудачей (Mobile Robot Guide, перепечатка automatedwarehouseonline.com)
A17: Горизонт расчета | B17: 5 | C17: лет | D17: D | F17: Отраслевой датасет по складам, лист "Склад": горизонт окупаемости 5 лет (3-10)
A18: Тариф на электроэнергию | B18: 9 | C18: ₽/кВт·ч | D18: F | F18: Нет подтвержденного источника: взять предельный уровень нерегулируемых цен на mosenergosbyt.ru, СН2/НН
A19: Рост зарплат в год | B19: 0.07 | C19: доля | D19: C | F19: Сценарные условия Минэкономразвития на 2027-2029, 12.05.2026, garant.ru/products/ipo/prime/doc/414115625/: +6,5% (2027), +6,9% (2028), +7,1% (2029), берем около 7%
A20: Перемещений паллет в сутки | B20: 2000 | C20: паллет/сут | D20: D | F20: Отраслевой датасет по складам, лист "Склад": приемка 1000 + отгрузка 1000
A21: Масса паллеты с грузом | B21: 800 | C21: кг | D21: D | F21: Отраслевой датасет по складам, лист "Склад": средняя масса грузовой единицы 800 кг (200-1500)
A22: Доля перевозок для роботов | B22: 0.95 | C22: доля | D22: D | F22: Отраслевой датасет по складам, лист "Склад": негабарит 5% остается ручным
A24: План объекта
A25: Здание | B25: 118 x 85 | C25: м
A26: Средний маршрут до буфера у ворот | B26: 65.7 | C26: м
A27: Мест у ворот | B27: 10 | C27: шт
A28: Проездов между рядами | B28: 18 | C28: шт
A29: Самый узкий проезд | B29: 3.5 | C29: м
A30: Верхний ярус | B30: 6.8 | C30: м
A31: Пандусов | B31: 0 | C31: шт

Sheet Источники
A1: Откуда цифры
A2: Склад, перевозка паллет между зонами · Ronavi H1500 (грузоподъемность до 1 500 кг) · расчет от 18.10.2026 22:58 мск · модель 0.2
A3: Предварительная оценка, не коммерческое предложение
A4: Доверие: S закон или норматив, A проверено, B сходятся два источника, C один источник, D только каталог ФЦ БАС или СМИ, E источники расходятся, F наше допущение
A5: Группа | B5: Значение | C5: Число | D5: Единица | E5: Доверие | F5: Источник | G5: Дата | H5: Путь в модели
A6: Решение | B6: Средняя мощность | C6: 0.72 | D6: кВт | E6: C | F6: Паспорт Ronavi H1500 (robob2b.ru): батарея 60 А*ч при 48 В, 2,88 кВт*ч, не менее 4 ч работы; 2,88 / 4 = 0,72 кВт, верхняя оценка средней мощности | G6: 2026-09 | H6: robots.ronavi-h1500.avg_power_kw
A7: Решение | B7: Средняя скорость | C7: 1 | D7: м/с | E7: C | F7: Ronavi, разбор цикла 24.04.2025: "Средняя скорость робота: 1 м/с. Длина маршрута в одну сторону: 60 м, полный цикл 120 м, около 120 секунд" | G7: 2025-04 | H7: robots.ronavi-h1500.avg_speed_m_s
A8: Решение | B8: Срок службы аккумулятора | C8: 3 | D8: лет | E8: D | F8: Отраслевой датасет по складам, лист "Легенда": замена АКБ раз в 3-5 лет; при работе 22 ч без выходных берем 3 | G8: 2026-09 | H8: robots.ronavi-h1500.battery_life_years
A9: Решение | B9: Цена аккумулятора | C9: 158000 | D9: ₽ | E9: D | F9: Паспорт Ronavi H1500: 2,88 кВт*ч * 55 000 руб; тяговая LiFePO4 48 В 100 А*ч за 168 800 и 265 200 руб (интеграторы, аналог), 35-55 тыс. руб за кВт*ч, берем худшее 55 тыс. | G9: 2026-09 | H9: robots.ronavi-h1500.battery_price_rub
A10: Решение | B10: Время зарядки | C10: 0.3 | D10: ч | E10: E | F10: Каталог ФЦ БАС catalog_export_v4: зарядка 0,3 ч, быстрая зарядка у производителя около 18 мин; полная по паспорту 80 мин (data/specs/specs.csv) | G10: 2026-09 | H10: robots.ronavi-h1500.charge_time_h
A11: Решение | B11: Цена зарядной станции | C11: 450000 | D11: ₽ | E11: C | F11: Ronavi Charger 450 000 руб, ronavi-robotics.ru/catalogue/charger (в статье Ronavi 2025 года 200-400 тыс.) | G11: 2026-09 | H11: robots.ronavi-h1500.charger_price_rub
A12: Решение | B12: Пусконаладка, доля цены | C12: 0.1 | D12: доля цены робота | E12: F | F12: Нет источника: доля от стоимости оборудования. У лизинговой CHG-MERIDIAN "+30% к оборудованию", но туда входит интеграция, которую мы считаем отдельно в затратах объекта | H12: robots.ronavi-h1500.commissioning_share
A13: Решение | B13: Погрузка и выгрузка за рейс | C13: 20 | D13: с | E13: C | F13: Сумма подтвержденного: подъем 3-6 с и опускание столько же (Geek+ P-series "Minimum Lifting Time 4 s", MiR EU Pallet Lift 60 мм при 10 мм/с), развороты 4-5 с (Geek+ "90°/1.5s"); доводка и ожидание у точки 5-10 с источника не имеют | G13: 2026-09 | H13: robots.ronavi-h1500.handling_s
A14: Решение | B14: Лицензия ПО в год | C14: 60000 | D14: ₽ в год на робота | E14: D | F14: Robotsman RMS: подписка 5 000 руб в месяц за робота (аналог: российская платформа управления роботами) | G14: 2026-09 | H14: robots.ronavi-h1500.license_rub_year
A15: Решение | B15: Обслуживание в год, доля цены | C15: 0.1 | D15: доля цены в год | E15: C | F15: Ronavi: обслуживание "около 10% от стоимости в год (~300 тыс. руб.)" для H1500 (блог Ronavi, 16.05.2025) | G15: 2026-09 | H15: robots.ronavi-h1500.maintenance_share_year
A16: Решение | B16: Рейсов в час по паспорту | C16: 0 | D16: рейсов в час | E16: F | F16: Не задан: 80-100 паллет/ч из отраслевых примеров дано для типовой короткой зоны, считаем от маршрута | G16: 2026-09 | H16: robots.ronavi-h1500.nominal_trips_per_hour
A17: Решение | B17: Внимание оператора, минут в час | C17: 1.5 | D17: мин в час | E17: F | F17: Считаем от сбоев: если робот требует внимания раз в 2-4 часа и на разбор уходит 3-5 минут, это 0,75-2,5 минуты в час, берем середину. Один оператор тянет около 40 роботов. Сама модель не наша: в исследованиях человеко-машинного взаимодействия это fan-out = 1 + время автономной работы / время вмешательства (Olsen, Goodrich). Эмпирика дает 4-6 роботов на оператора для телеуправляемых машин и 100+ для автономных роев, склад ближе ко второму. Конкретной цифры для складских AMR никто не публикует, поэтому оценка остается F | G17: 2026-09 | H17: robots.ronavi-h1500.operator_attention_min_per_hour
A18: Решение | B18: Цена робота | C18: 2700000 | D18: ₽ | E18: B | F18: Каталог роботизированных решений ФЦ БАС (с НДС); на сайте производителя 2,16-2,7 млн | G18: 2026-09 | H18: robots.ronavi-h1500.price_rub
A19: Решение | B19: Срок договора аренды | C19: 36 | D19: мес. | E19: C | F19: Яндекс Роботикс: подписка на 36 мес; Ronavi: оплата за действие от ~30 мес (ronavi-robotics.ru/pricing) | G19: 2026-09 | H19: robots.ronavi-h1500.raas.contract_months
A20: Решение | B20: Ответственность за порчу в аренде | C20: 0.01 | D20: доля цены в год | E20: F | F20: Нет источника: условие договора аренды | H20: robots.ronavi-h1500.raas.damage_share_year
A21: Решение | B21: Аренда в месяц | C21: 100000 | D21: ₽ в месяц за робота | E21: D | F21: Ronavi H1500 по подписке "от 100 тыс. руб. в месяц", пресс-релиз РОСНАНО 27.09.2019, rusnano.com; цена 2019 года без индексации | G21: 2026-09 | H21: robots.ronavi-h1500.raas.fee_rub_month
A22: Решение | B22: Присмотр за парком в аренде | C22: 0 | D22: доля | E22: F | F22: Сколько присмотра за парком берет на себя поставщик при аренде. У Автомакона в платеж входят "мониторинг и поддержка 24/7, диагностика, техническое обслуживание, запасные части, ремонт", у Ronavi "техподдержка и ПО". Но разбирать сбой на месте все равно кому-то надо, а доли никто не публикует. По умолчанию ноль: присмотр целиком на клиенте | H22: robots.ronavi-h1500.raas.support_share
A23: Решение | B23: Роботов на одну зарядку | C23: 4 | D23: роботов | E23: C | F23: Ronavi: "одна станция рассчитана на 4-5 роботов" (блог Ronavi, 24.04.2025), берем худшее 4 | G23: 2026-09 | H23: robots.ronavi-h1500.robots_per_charger
A24: Решение | B24: Работа от одной зарядки | C24: 6 | D24: ч | E24: E | F24: Каталог ФЦ БАС catalog_export_v4: 6 ч работы от батареи. У производителя на сайте до 10 ч на окне заряда 80-20%, в паспорте (robob2b.ru) не менее 4 ч. По правилам данных остается цифра каталога ФЦ БАС (data/specs/specs.csv) | G24: 2026-09 | H24: robots.ronavi-h1500.run_time_h
A25: Решение | B25: Срок службы робота | C25: 5 | D25: лет | E25: C | F25: Постановление № 1: промышленные транспортные роботы (ОКОФ 330.28.99.39.213), 3 группа 3-5 лет, audit-it.ru | G25: 2026-09 | H25: robots.ronavi-h1500.service_life_years
A26: Решение | B26: ПО управления парком | C26: 1500000 | D26: ₽ | E26: D | F26: Ronavi: внедрение RMS 0,5-2 млн руб на проект; Robotsman RMS: бессрочная лицензия от 1 млн руб. Интеграцию с WMS считаем отдельно в затратах объекта | G26: 2026-09 | H26: robots.ronavi-h1500.software_rub
A27: Решение | B27: Цена станции комплектации | C27: 0 | D27: ₽ | E27: F | F27: Не нужна для перевозки | G27: 2026-09 | H27: robots.ronavi-h1500.station_price_rub
A28: Решение | B28: Загрузка робота | C28: 0.75 | D28: доля | E28: B | F28: Отраслевой датасет по складам, лист "Легенда": загрузка AMR 70-85% (зарядка, простои, ожидание). Сходится с Ronavi: подзарядка 10-15 мин каждые 45-50 мин работы | G28: 2026-09 | H28: robots.ronavi-h1500.utilization
A29: Деньги, налоги, цены | B29: Рабочих часов в году на ставку | C29: 1972 | D29: ч в год | E29: S | F29: Производственный календарь 2026, 40-часовая неделя, consultant.ru/law/ref/calendar/proizvodstvennye/2026/ | G29: 2026-09 | H29: economics.annual_work_hours
A30: Деньги, налоги, цены | B30: Резерв на непредвиденное, доля вложений | C30: 0.1 | D30: доля | E30: D | F30: Отраслевой датасет по складам, лист "Легенда": CAPEX включает резерв 10% | G30: 2026-09 | H30: economics.capex_reserve_share
A31: Деньги, налоги, цены | B31: Ставка дисконтирования | C31: 0.14 | D31: доля в год | E31: C | F31: Ключевая ставка ЦБ 14,00%, решение 11.09.2026, без премии за риск | G31: 2026-09 | H31: economics.discount_rate
A32: Деньги, налоги, цены | B32: Рост цены электроэнергии в год | C32: 0.09 | D32: доля в год | E32: C | F32: Сценарные условия Минэкономразвития на 2027-2029, 12.05.2026, garant.ru/products/ipo/prime/doc/414115625/: сетевые тарифы для прочих +13,0% (2027), +8,9% (2028), +6,3% (2029), в среднем около 9% | G32: 2026-09 | H32: economics.energy_price_growth
A33: Деньги, налоги, цены | B33: Тариф на электроэнергию | C33: 9 | D33: ₽ за кВт·ч | E33: F | F33: Нет подтвержденного источника: взять предельный уровень нерегулируемых цен на mosenergosbyt.ru, СН2/НН | H33: economics.energy_price_rub_kwh
A34: Деньги, налоги, цены | B34: Горизонт расчета | C34: 5 | D34: лет | E34: D | F34: Отраслевой датасет по складам, лист "Склад": горизонт окупаемости 5 лет (3-10) | G34: 2026-09 | H34: economics.horizon_years
A35: Деньги, налоги, цены | B35: Инфляция в год | C35: 0.04 | D35: доля в год | E35: C | F35: Прогноз ЦБ 11.09.2026: 4,0% в 2027; МЭР: 4,0% в 2027-2029 | G35: 2026-09 | H35: economics.inflation
A36: Деньги, налоги, цены | B36: Границы оценки окупаемости, лет | C36: 3 - 5 | D36: лет | E36: S | F36: ТЗ, п. 3.5.7: интервалы до 3 лет, 3-5 лет, более 5 лет | G36: 2026-09 | H36: economics.payback_bands_years
A37: Деньги, налоги, цены | B37: Найм одного человека, окладов | C37: 0 | D37: окладов | E37: F | F37: Нет источника, пока не учитываем | H37: economics.payroll.hire_cost_months
A38: Деньги, налоги, цены | B38: Взнос от несчастных случаев | C38: 0.006 | D38: доля оклада | E38: S | F38: ОКВЭД 52.10: 5 класс профриска (приказ Минтруда 851н), тариф 0,6% (179-ФЗ, 434-ФЗ). В датасете 0,2% | G38: 2026-09 | H38: economics.payroll.injury_insurance_rate
A39: Деньги, налоги, цены | B39: Предельная база страховых взносов | C39: 2979000 | D39: ₽ в год | E39: S | F39: Постановление Правительства от 31.10.2025 № 1705 | G39: 2026-09 | H39: economics.payroll.insurance_base_limit_rub
A40: Деньги, налоги, цены | B40: Страховые взносы | C40: 0.3 | D40: доля оклада | E40: S | F40: НК РФ ст. 425, редакция 04.08.2026 | G40: 2026-09 | H40: economics.payroll.insurance_rate
A41: Деньги, налоги, цены | B41: Взносы сверх предельной базы | C41: 0.151 | D41: доля оклада | E41: S | F41: НК РФ ст. 425, редакция 04.08.2026 | G41: 2026-09 | H41: economics.payroll.insurance_rate_above_limit
A42: Деньги, налоги, цены | B42: Текучесть персонала в год | C42: 0 | D42: доля в год | E42: F | F42: Для склада в датасете нет, пока не учитываем | H42: economics.payroll.turnover_rate
A43: Деньги, налоги, цены | B43: Спецодежда на человека в год | C43: 0 | D43: ₽ в год | E43: F | F43: Нет источника, пока не учитываем | H43: economics.payroll.workwear_rub_year
A44: Деньги, налоги, цены | B44: Запас парка на пик | C44: 0.15 | D44: доля | E44: D | F44: Отраслевой датасет по складам, лист "Легенда": резерв 15-20%, берем нижнюю границу | G44: 2026-09 | H44: economics.peak_reserve_share
A45: Деньги, налоги, цены | B45: Начало первой смены | C45: 6 | D45: ч | E45: F | F45: Допущение команды: первая смена начинается в 06:00, поэтому ночные часы это часы работы сверх 16 в сутки | H45: economics.peak_staffing.day_start_h
A46: Деньги, налоги, цены | B46: Доплата за ночные часы | C46: 0.2 | D46: доля | E46: S | F46: ТК РФ ст. 154 и постановление Правительства № 554 от 22.07.2008: час работы с 22:00 до 06:00 оплачивается не меньше чем на 20% выше | G46: 2026-10 | H46: economics.peak_staffing.night_surcharge
A47: Деньги, налоги, цены | B47: Час временного персонала в пик | C47: 320 | D47: ₽ в час | E47: C | F47: Аутстаффинг складского персонала, Москва и Санкт-Петербург: 320-650 руб/ч (прайсы algorithm24.ru/tseny и spb.leaderg.ru/autsorsing/skladskogo-personala, сверка 17.10.2026), берем нижнюю: выгода роботов от пика не завышена | G47: 2026-10 | H47: economics.peak_staffing.temp_rate_rub_hour
A48: Деньги, налоги, цены | B48: Окупаемость покупки у реальных внедрений, лет | C48: 2 - 3 | D48: лет | E48: C | F48: Окупаемость покупки, страницы открыты 16.10.2026. ВкусВилл, AGV Автомакона: "должен окупиться за два-три года", прогноз интегратора (habr.com/ru/companies/automacon/articles/881120, 11.02.2025). Яндекс Лавка: окупаемость "около трех лет" (journal.reindustry-expo.ru/yandeks-lavka-i-yandeks-robotiks, 25.06.2026). RangePlus, Geek+, Великобритания: "full return on investment in less than two years" (geekplus.com/case-studies, 20.06.2025). Только у покупки: у аренды и оплаты за действие один кейс, Восток-Сервис, 6 месяцев, диапазона из него нет | G48: 2026-10 | H48: economics.plausibility.payback_years
A49: Деньги, налоги, цены | B49: Сокращение людей на отборе у реальных внедрений | C49: 0.55 - 0.8 | D49: доля | E49: C | F49: Внедрения отбора, страницы открыты 16.10.2026. Восток-Сервис: "-2,2x к численности" на странице Ronavi, у Retail.ru втрое (28.06.2024), берем скромное 0,55, как в docs/staff.md. ACCA, Geek+, Япония: "Workforce reduced from 20 to 4 staff" (PDF Geek+, 3PL-ACCA-Case-study), 0,8. Fleet Feet, Locus, США: было 20-25 отборщиков, стало пять (locusrobotics.com/resources/case-study/fleet-feet-and-korber-supply-chain-software), 0,75-0,8. Вне диапазона Яндекс Лавка (людей не убавилось, вырос объем) и инвентаризация ВкусВилла (другая операция) | G49: 2026-10 | H49: economics.plausibility.staff_cut_share
A50: Деньги, налоги, цены | B50: Ставка НДС | C50: 0.22 | D50: доля | E50: A | F50: НДС 22% с 01.01.2026, Федеральный закон от 28.11.2025 № 425-ФЗ (expert.ru/news/vladimir-putin-podpisal-zakon-o-povyshenii-nds-do-22/) | G50: 2026-10 | H50: economics.vat.rate
A51: Деньги, налоги, цены | B51: Компания возвращает НДС? | C51: 0 | D51: 1 да, 0 нет | E51: F | F51: Выбор клиента: 1 компания не возвращает НДС (упрощенка без НДС), считаем цены с НДС; 0 возвращает, цены без НДС. По умолчанию 0: склад на общей системе налогов возвращает входной НДС, и с 2026 года на НДС переходят компании на УСН с выручкой больше 20 млн (425-ФЗ) | G51: 2026-10 | H51: economics.vat.with_vat
A52: Деньги, налоги, цены | B52: Рост зарплат в год | C52: 0.07 | D52: доля в год | E52: C | F52: Сценарные условия Минэкономразвития на 2027-2029, 12.05.2026, garant.ru/products/ipo/prime/doc/414115625/: +6,5% (2027), +6,9% (2028), +7,1% (2029), берем около 7% | G52: 2026-09 | H52: economics.wage_growth
A53: Объект и задачи | B53: Площадь зоны работы роботов | C53: 10000 | D53: м² | E53: D | F53: Отраслевой датасет по складам, лист "Склад" | G53: 2026-09 | H53: facilities.warehouse.active_area_m2
A54: Объект и задачи | B54: Ширина проезда между рядами | C54: 2800 | D54: мм | E54: D | F54: Отраслевой датасет по складам, лист "Склад": ширина рабочих проходов между стеллажами 2,8 м (1,5-4,5) | G54: 2026-09 | H54: facilities.warehouse.constraints.aisle_width_mm
A55: Объект и задачи | B55: Высота потолка | C55: 10 | D55: м | E55: D | F55: Отраслевой датасет по складам, лист "Склад": высота потолков в зоне хранения 10 м (5-16) | G55: 2026-09 | H55: facilities.warehouse.constraints.ceiling_m
A56: Объект и задачи | B56: Ровность пола | C56: 3 | D56: мм | E56: D | F56: Отраслевой датасет по складам, лист "Склад": отклонение 3 мм на 2 м (1-8), DIN 15185 или FM2 | G56: 2026-09 | H56: facilities.warehouse.constraints.floor_flatness_mm
A57: Объект и задачи | B57: Ширина главного проезда | C57: 3500 | D57: мм | E57: D | F57: Отраслевой датасет по складам, лист "Склад": ширина главных проездов 3,5 м (2,5-6) | G57: 2026-09 | H57: facilities.warehouse.constraints.main_aisle_width_mm
A58: Объект и задачи | B58: Доля отборов ходового товара | C58: 0.75 | D58: доля | E58: C | F58: Bartholdi, Hackman. Warehouse & Distribution Science, версия 0.98.1 от 17.08.2019, рис. 14.1, с. 241: 5000 самых ходовых из 25 000 SKU дают больше 75% отборов; warehouse-science.com. Популярное правило 80/20 встречается только во вторичных источниках | G58: 2026-09 | H58: facilities.warehouse.fast_picks_share
A59: Объект и задачи | B59: Доля ходового товара | C59: 0.2 | D59: доля | E59: D | F59: Отраслевой датасет по складам, лист "Склад": доля SKU с быстрым оборотом (A-класс) 20% (10-40%). Считаем, что у каждой позиции свое место у стеллажа | G59: 2026-09 | H59: facilities.warehouse.fast_share
A60: Объект и задачи | B60: С какого парка нужна своя связь | C60: 3 | D60: роботов | E60: F | F60: Нет источника: на 1-2 робота хватает Wi-Fi, который на складе уже есть, отдельную связь не закладываем | G60: 2026-10 | H60: facilities.warehouse.implementation.communications_min_fleet
A61: Объект и задачи | B61: Связь и сеть в год | C61: 300000 | D61: ₽ в год | E61: F | F61: Нет источника: связь роботов (точки Wi-Fi, сервер) на проект около 10 роботов. В расчете от числа роботов: на робота 300 000 / 10 = 30 000 в год, при 1-2 роботах не берем (communications_min_fleet) | H61: facilities.warehouse.implementation.communications_rub_year
A62: Объект и задачи | B62: Подбор оператора | C62: 50000 | D62: ₽ на человека | E62: F | F62: Нет источника: подбор оператора роботов с рынка, если замененных людей не хватает. Вакансии такие есть (RWB, X5 Tech), стоимости подбора нет | H62: facilities.warehouse.implementation.hiring_rub_per_person
A63: Объект и задачи | B63: Инфраструктура объекта | C63: 3000000 | D63: ₽ | E63: F | F63: Нет источника | H63: facilities.warehouse.implementation.infrastructure_rub
A64: Объект и задачи | B64: Интеграция с WMS | C64: 5000000 | D64: ₽ | E64: F | F64: Нет источника, нужно КП интегратора | H64: facilities.warehouse.implementation.integration_rub
A65: Объект и задачи | B65: Переобучение одного человека | C65: 10000 | D65: ₽ на человека | E65: C | F65: Курсы ДПО "оператор механизированных и автоматизированных складов": 5 000 руб (Grand School, 80 ч) и 12 491 руб (ЕВИДПО, 72 ч). Срок сходится с Ronavi: обучение оператора 1-2 недели | G65: 2026-09 | H65: facilities.warehouse.implementation.retraining_rub_per_person
A66: Объект и задачи | B66: Постоянные вложения пилота, доля | C66: 0.2 | D66: доля | E66: E | F66: Пилот на 1-2 робота: у Умного Сервиса манипулятор и паллетный FMR вместе с внедрением стоили 4-5 млн (umserv.ru, кейс 13.08.2025), значит постоянная часть не больше 1-2 млн; 20% от 9,5 млн это 1,9 млн | G66: 2026-10 | H66: facilities.warehouse.implementation.scale_min_share
A67: Объект и задачи | B67: Проект, на который даны постоянные вложения | C67: 10 | D67: роботов | E67: F | F67: Интеграцию 5 млн, инфраструктуру 3 млн и ПО 1,5 млн брали на демо-проект около 10 роботов. Нет источника | G67: 2026-10 | H67: facilities.warehouse.implementation.scale_ref_fleet
A68: Объект и задачи | B68: Минимум операторов в смене | C68: 0 | D68: человек в смену | E68: F | F68: Выбор пользователя: сколько дежурных по роботам держать в смене всегда, сверх присмотра по нагрузке. По умолчанию 0: присмотр считаем долей поста от минут внимания на робота, это часть работы начальника смены или оператора соседней зоны. Норматива роботов на оператора для складских AMR никто не публикует; Vecna Robotics на первых внедрениях видела 1 человека на 4-10 роботов и называет это неудачей (Mobile Robot Guide, перепечатка automatedwarehouseonline.com) | G68: 2026-10 | H68: facilities.warehouse.min_operator_posts
A69: Объект и задачи | B69: Доля перевозок для роботов | C69: 0.95 | D69: доля | E69: D | F69: Отраслевой датасет по складам, лист "Склад": негабарит 5% остается ручным | G69: 2026-09 | H69: facilities.warehouse.operations.pallet_transport.automatable_share
A70: Объект и задачи | B70: Доля работы людей, которую забирает робот, перевозка паллет между зонами | C70: 0.74 | D70: доля | E70: E | F70: Оценка команды: робот повторяет перевозку по полу, у человека она занимает примерно столько же, сколько цикл робота: 2 * 65,7 м / 1 м/с + 20 с = 151 с (маршрут типового плана, скорость и погрузка Ronavi, C), из 195 с на паллету при выработке 18,5 в час (3 600 / 18,5). Доля 151 / 195 = 0,78, без 5% негабарита 0,95 * 0,78 = 0,74. Сверка: у Умного Сервиса паллетный робот заменяет 0,6 человека в смену при работе 24/7 (umserv.ru, C), X5 на 67 автономных погрузчиках ждет сокращения штата РЦ до 20% (retail.ru, 04.06.2026, A): доля работы, а не 95% | G70: 2026-10 | H70: facilities.warehouse.operations.pallet_transport.labor_share
A71: Объект и задачи | B71: Масса паллеты с грузом | C71: 800 | D71: кг | E71: D | F71: Отраслевой датасет по складам, лист "Склад": средняя масса грузовой единицы 800 кг (200-1500) | G71: 2026-09 | H71: facilities.warehouse.operations.pallet_transport.load_kg
A72: Объект и задачи | B72: Операций за один рейс, перевозка паллет между зонами | C72: 1 | D72: операций | E72: S | F72: Одна паллета за рейс | G72: 2026-09 | H72: facilities.warehouse.operations.pallet_transport.ops_per_trip
A73: Объект и задачи | B73: Перемещений паллет в сутки | C73: 2000 | D73: в сутки | E73: D | F73: Отраслевой датасет по складам, лист "Склад": приемка 1000 + отгрузка 1000 | G73: 2026-09 | H73: facilities.warehouse.operations.pallet_transport.volume_per_day
A74: Объект и задачи | B74: Надбавка оператору роботов | C74: 0 | D74: доля | E74: F | F74: Оператор робозоны это переученный сотрудник той же роли. Яндекс Роботикс, раздел "Персонал": "Сотрудники на точках отбора — операторы роботов". Надбавку за роботов никто не публикует, поэтому пока ноль. Для сравнения: сервисный инженер по роботам в Москве стоит 138-207 тыс. gross (4 вакансии hh.ru, сентябрь 2026), но это другая профессия | H74: facilities.warehouse.operator_salary_premium
A75: Объект и задачи | B75: Пиковый коэффициент нагрузки | C75: 1.5 | D75: раза | E75: D | F75: Отраслевой датасет по складам, лист "Склад" | G75: 2026-09 | H75: facilities.warehouse.peak_factor
A76: Объект и задачи | B76: Часть склада под отбор роботами | C76: 0.1 | D76: доля | E76: D | F76: Часть зоны работы роботов под робозону штучного отбора. Посчитано: парк по формуле 20 Ronavi M * 50 м2 на робота (engine.geometry.picking_m2_per_robot) = 1 000 м2 из 10 000 м2. Правит человек на первом шаге | G76: 2026-10 | H76: facilities.warehouse.picking_zone_share
A77: Объект и задачи | B77: Рабочих дней в году | C77: 365 | D77: дней | E77: B | F77: Режим склада без выходных, сверка 19.10.2026. В датасете, лист "Склад", 2 смены по 11 ч 365 дней, и так работают склады обоих типов: РЦ Магнита в Подольске 2/2 по 11 ч с ночными часами (hh.ru/vacancy/135864165, 15.10.2026), Ленты в Валищево 2/2 по 12 ч (hh.ru/vacancy/135995269), FM Logistic Белый Раст 2/2 день и ночь по 12 ч (hh.ru/vacancy/135967197), Мегамаркет в Москве 2/2 ночь 20:00-08:00 (hh.ru/vacancy/135946119), даркстор Лавки ночь 21:00-9:00 (hh.ru/vacancy/135852510, 28.09.2026). Пятидневки 2 смены по 8 ч у РЦ и фулфилмента не нашли. Берем 22 часа датасета, а не 24 у вакансий: так экономия не завышена. Свой режим человек ставит на шаге параметров (docs/decisions.md, "Типовой режим склада") | G77: 2026-10 | H77: facilities.warehouse.schedule.days_per_year
A78: Объект и задачи | B78: Продолжительность смены | C78: 11 | D78: ч | E78: B | F78: Режим склада без выходных, сверка 19.10.2026. В датасете, лист "Склад", 2 смены по 11 ч 365 дней, и так работают склады обоих типов: РЦ Магнита в Подольске 2/2 по 11 ч с ночными часами (hh.ru/vacancy/135864165, 15.10.2026), Ленты в Валищево 2/2 по 12 ч (hh.ru/vacancy/135995269), FM Logistic Белый Раст 2/2 день и ночь по 12 ч (hh.ru/vacancy/135967197), Мегамаркет в Москве 2/2 ночь 20:00-08:00 (hh.ru/vacancy/135946119), даркстор Лавки ночь 21:00-9:00 (hh.ru/vacancy/135852510, 28.09.2026). Пятидневки 2 смены по 8 ч у РЦ и фулфилмента не нашли. Берем 22 часа датасета, а не 24 у вакансий: так экономия не завышена. Свой режим человек ставит на шаге параметров (docs/decisions.md, "Типовой режим склада") | G78: 2026-10 | H78: facilities.warehouse.schedule.shift_hours
A79: Объект и задачи | B79: Смен в сутки | C79: 2 | D79: смен | E79: B | F79: Отраслевой датасет по складам, лист "Склад"; сходится с вакансиями РЦ и фулфилмента 2/2 день и ночь (docs/decisions.md, "Типовой режим склада") | G79: 2026-10 | H79: facilities.warehouse.schedule.shifts
A80: Объект и задачи | B80: Активных SKU | C80: 2000 | D80: SKU | E80: D | F80: Отраслевой датасет по складам, лист "Склад": активных SKU 2000 (1000-10000). В расчет не входит, описание склада для отчета | G80: 2026-09 | H80: facilities.warehouse.sku_count
A81: Объект и задачи | B81: Товар разложен по ходовости | C81: 0 | D81: 1 да, 0 нет | E81: F | F81: Выбор клиента: разложен ли товар по ходовости, 1 да, 0 нет. По умолчанию нет: так расчет осторожнее, а на Восток-Сервисе роботов и без этого вышло вдвое больше нашей формулы | H81: facilities.warehouse.slotted_by_turnover
A82: Объект и задачи | B82: Потери рабочего времени | C82: 0.25 | D82: доля | E82: D | F82: Отраслевой датасет по складам, лист "Склад": +25% к нормативной численности | G82: 2026-09 | H82: facilities.warehouse.staff_loss_share
A83: Допущения модели | B83: Площадь робозоны на робота отбора | C83: 50 | D83: м² | E83: C | F83: Кейсы внедрений, страницы открыты 29.09.2026. Decathlon Куньшань, Geek+ P800, blog.geekplus.com: "46 P800 robots", "project area is about 2,000 square meters", "7 picking stations" - 43 м2 на робота. HIK, Япония, en.myrobotsolution.com: "181 AMRs", "26 workstations", warehouse "spanning over 11,000 m2" - 61 м2 на робота. Geek+ в Китае (nissa-eng.ru не открылся, страница-тег blog.geekplus.com без цифр по конкретному складу) и Tmall (thewirechina.com за платным доступом) не подтвердились. По двум подтвержденным случаям 43-61, среднее около 52, оставляем 50 между ними | G83: 2026-09 | H83: engine.geometry.picking_m2_per_robot
A84: Допущения модели | B84: Поправка маршрута на повороты и объезды | C84: 0.75 | D84: от стороны зоны | E84: F | F84: Геометрия: квадратная зона, ворота посередине стороны, движение по проходам: среднее расстояние 0,25 + 0,5 стороны | G84: 2026-09 | H84: engine.geometry.route_factor
A85: Допущения модели | B85: Запас высоты подъема над ярусом | C85: 1000 | D85: мм | E85: F | F85: Наше правило: подъем до метра это подхват паллеты с пола, выше это штабелирование в стеллаж. Только штабелерам проверяем, достают ли они до верхнего яруса | H85: engine.selection.stacking_lift_mm
A86: Допущения модели | B86: Роботов в строю | C86: 0.9 | D86: доля | E86: F | F86: Что остается от коэффициента загрузки после симуляции: очереди и зарядку она считает сама, остаются плановое ТО и мелкие простои. Источника нет, допущение команды | H86: engine.simulation.availability
A87: Допущения модели | B87: Часов пика в смене | C87: 2 | D87: ч | E87: F | F87: Нет источника: сколько длится пик. Датасет дает только отношение пикового часа к среднему (лист "Склад", 1,5), форму дня для склада не публикует никто. Берем два часа, допущение команды | H87: engine.simulation.peak_hours
A88: Допущения модели | B88: Роботов в одном проезде | C88: 3 | D88: роботов | E88: F | F88: Сколько роботов помещаются в одной части проезда между рядами, от поперечного проезда до поперечного. Источника нет: зависит от длины части и дистанции между роботами, допущение команды | H88: engine.simulation.robots_per_aisle
A89: Как платим за покупку | B89: Способ оплаты покупки | C89: 0 | D89: 0 свои, 1 кредит, 2 лизинг | E89: S | F89: Выбор пользователя: 0 свои деньги, 1 кредит, 2 лизинг. По умолчанию свои деньги: так считает базовый сценарий в Дополнениях к ТЗ, п. 2.1 | G89: 2026-09 | H89: financing.method
A90: Выход на режим | B90: Выход на режим: эффект в первый месяц, перевозка и уборка | C90: 0.7 | D90: доля | E90: F | F90: Нет источника: сколько эффекта дают роботы в первый месяц. Про простые AMR пишут "up and running in days, not months" (Locus Robotics, Rapid Deployment), пилот Ronavi около 4 недель (ronavi-robotics.ru/industry/3pl); просадку 10-20% в первые две недели называет JIT Transportation без источника | H90: ramp_up.simple.first_month_share
A91: Выход на режим | B91: Выход на режим: месяцев до полного эффекта, перевозка и уборка | C91: 1 | D91: мес. | E91: F | F91: Нет источника: через сколько месяцев выход на полный эффект. Внедрение простых AMR 4-8 недель (6 River Systems, Ronavi) | H91: ramp_up.simple.months
